nlbook/__init__.py
nlbook/gemini.py
nlbook/main.py
nlbook/nlbook.py
nlbook/css/font-awesome.css
nlbook/css/font-awesome.min.css
nlbook/css/main.css
nlbook/css/prism.min.css
nlbook/fonts/FontAwesome.otf
nlbook/fonts/fontawesome-webfont.eot
nlbook/fonts/fontawesome-webfont.svg
nlbook/fonts/fontawesome-webfont.ttf
nlbook/fonts/fontawesome-webfont.woff
nlbook/fonts/fontawesome-webfont.woff2
nlbook/js/CodeCell.js
nlbook/js/ExplanationEditor.js
nlbook/js/MarkdownCell.js
nlbook/js/OutputRenderer.js
nlbook/js/ValidationCell.js
nlbook/js/markdown-it.min.js
nlbook/js/nb.js
nlbook/js/prism-python.min.js
nlbook/js/prism.min.js
nlbook/js/vue.esm-browser.js
nlbook/views/index.html
nlbook-0.0.5.dist-info/licenses/LICENSE.md
nlbook-0.0.5.dist-info/METADATA
nlbook-0.0.5.dist-info/WHEEL
nlbook-0.0.5.dist-info/entry_points.txt
nlbook-0.0.5.dist-info/top_level.txt
nlbook-0.0.5.dist-info/RECORD
